mvskew/__init__.py
mvskew/_mv_samplers_utils.py
mvskew/mv_samplers.py
mvskew/mv_samplers_dev.py
mvskew-0.0.2.dist-info/LICENSE
mvskew-0.0.2.dist-info/METADATA
mvskew-0.0.2.dist-info/WHEEL
mvskew-0.0.2.dist-info/top_level.txt
mvskew-0.0.2.dist-info/RECORD
