Metadata-Version: 2.1
Name: mvskew
Version: 0.0.2
Summary: Multivariate skew distribution samplers
Home-page: https://github.com/SvenSerneels/mvskew
Author: Sven Serneels
Author-email: svenserneels@gmail.com
License: UNKNOWN
Platform: UNKNOWN
Classifier: Programming Language :: Python :: 3
Classifier: License :: OSI Approved :: MIT License
Classifier: Operating System :: OS Independent
Requires-Dist: numpy (>=1.5.0)
Requires-Dist: scipy (>=0.8.0)
